bsr/__init__.py
bsr/blender_commands/file.py
bsr/blender_commands/macros.py
bsr/geometry/__init__.py
bsr/geometry/composite/__init__.py
bsr/geometry/composite/rod.py
bsr/geometry/composite/stack.py
bsr/geometry/primitives/__init__.py
bsr/geometry/primitives/simple.py
bsr/geometry/protocol.py
bsr/protocol.py
bsr/tools/keyframe_mixin.py
bsr/tools/protocol.py
elastica_blender/__init__.py
elastica_blender/converter/__init__.py
elastica_blender/converter/npz2blend.py
elastica_blender/rod_callback.py
bsr-0.1.1.dist-info/METADATA
bsr-0.1.1.dist-info/WHEEL
bsr-0.1.1.dist-info/entry_points.txt
bsr-0.1.1.dist-info/RECORD
