Metadata-Version: 2.1
Name: bsr
Version: 0.1.1
Summary: Blender integration tools for soft-rod system.
License: MIT
Keywords: data-analysis
Requires-Python: >=3.10,<3.12
Classifier: Development Status :: 4 - Beta
Classifier: Intended Audience :: Education
Classifier: Intended Audience :: Science/Research
Classifier: License :: OSI Approved :: MIT License
Classifier: Operating System :: OS Independent
Classifier: Programming Language :: Python :: 3
Classifier: Programming Language :: Python :: 3.10
Classifier: Programming Language :: Python :: 3.11
Requires-Dist: bpy (==4.0.0) ; python_version >= "3.10.dev0" and python_version < "3.11.dev0"
Requires-Dist: bpy (==4.1.0) ; python_version >= "3.11.dev0" and python_version < "3.12.dev0"
Requires-Dist: click (>=8.1.7,<9.0.0)
Requires-Dist: mathutils (>=3.3.0,<4.0.0)
